odoo/addons/report_batch/README.rst
odoo/addons/report_batch/__init__.py
odoo/addons/report_batch/__manifest__.py
odoo/addons/report_batch/i18n/report_batch.pot
odoo/addons/report_batch/models/__init__.py
odoo/addons/report_batch/models/ir_action_report.py
odoo/addons/report_batch/readme/CONFIGURE.rst
odoo/addons/report_batch/readme/CONTRIBUTORS.rst
odoo/addons/report_batch/readme/CREDITS.rst
odoo/addons/report_batch/readme/DESCRIPTION.rst
odoo/addons/report_batch/readme/USAGE.rst
odoo/addons/report_batch/security/ir.model.access.csv
odoo/addons/report_batch/static/description/icon.png
odoo/addons/report_batch/static/description/index.html
odoo/addons/report_batch/tests/__init__.py
odoo/addons/report_batch/tests/test_report_batch.py
odoo/addons/report_batch/views/ir_action_report_view.xml
odoo13_addon_report_batch-13.0.1.0.1.dist-info/METADATA
odoo13_addon_report_batch-13.0.1.0.1.dist-info/WHEEL
odoo13_addon_report_batch-13.0.1.0.1.dist-info/top_level.txt
odoo13_addon_report_batch-13.0.1.0.1.dist-info/RECORD
